yunxiaoapi/__init__.py
yunxiaoapi/login.py
yunxiaoapi-1.0.0.dist-info/METADATA
yunxiaoapi-1.0.0.dist-info/WHEEL
yunxiaoapi-1.0.0.dist-info/top_level.txt
yunxiaoapi-1.0.0.dist-info/RECORD
